[{"Name": "???","Emotion": "Zangado","Text": "SAI DAQUI HUMANO, ESSA MAGIA SER DO GOB!"},
{"Name": "????","Emotion": "Zangado","Text": "CALA A BOCA GOB, A MAGIA SER DO BOG!"},
{"Name": "Gob","Emotion": "Zangado","Text": "HAHAHAHA! VOCÊ MUITO BURRO PRA USAR MAGIA, BOG! A CABEÇA DO GOB QUE CONTROLAR A MAGIA!"},
{"Name": "Bog","Emotion": "Zangado","Text": "GOB QUE SER BURRO! BOG VAI ARRANCAR CABEÇA IDIOTA DO GOB POR ISSO!"},
{"Name": "Tulius Spellbreaker","Emotion": "Confuso","Text": "..."},
{"Name": "Gob","Emotion": "Zangado","Text": "ME LARGA BOG! O HUMANO VAI FUGIR COM A MAGIA!"}
]
